xcode_mcp_server/__init__.py
xcode_mcp_server/__main__.py
xcode_mcp_server/cli.py
xcode_mcp_server/config_manager.py
xcode_mcp_server/config_ui.py
xcode_mcp_server/exceptions.py
xcode_mcp_server/security.py
xcode_mcp_server/server.py
xcode_mcp_server/tools/__init__.py
xcode_mcp_server/tools/build_project.py
xcode_mcp_server/tools/clean_project.py
xcode_mcp_server/tools/debug_list_notification_history.py
xcode_mcp_server/tools/get_build_errors.py
xcode_mcp_server/tools/get_build_results.py
xcode_mcp_server/tools/get_directory_listing.py
xcode_mcp_server/tools/get_directory_tree.py
xcode_mcp_server/tools/get_latest_test_results.py
xcode_mcp_server/tools/get_project_schemes.py
xcode_mcp_server/tools/get_runtime_output.py
xcode_mcp_server/tools/get_xcode_projects.py
xcode_mcp_server/tools/list_booted_simulators.py
xcode_mcp_server/tools/list_mac_app_windows.py
xcode_mcp_server/tools/list_project_tests.py
xcode_mcp_server/tools/list_running_mac_apps.py
xcode_mcp_server/tools/run_project_tests.py
xcode_mcp_server/tools/run_project_unmonitored.py
xcode_mcp_server/tools/run_project_until_terminated.py
xcode_mcp_server/tools/run_project_with_user_interaction.py
xcode_mcp_server/tools/stop_project.py
xcode_mcp_server/tools/take_app_screenshot.py
xcode_mcp_server/tools/take_simulator_screenshot.py
xcode_mcp_server/tools/take_window_screenshot.py
xcode_mcp_server/tools/take_xcode_screenshot.py
xcode_mcp_server/tools/version.py
xcode_mcp_server/utils/__init__.py
xcode_mcp_server/utils/applescript.py
xcode_mcp_server/utils/build_log_parser.py
xcode_mcp_server/utils/decode_xcode_recents.swift
xcode_mcp_server/utils/screenshot.py
xcode_mcp_server/utils/xcresult.py
xcode_mcp_server-1.3.2.dist-info/METADATA
xcode_mcp_server-1.3.2.dist-info/WHEEL
xcode_mcp_server-1.3.2.dist-info/entry_points.txt
xcode_mcp_server-1.3.2.dist-info/licenses/LICENSE
xcode_mcp_server-1.3.2.dist-info/RECORD
