Metadata-Version: 2.4
Name: xcode-mcp-server
Version: 1.3.2
Summary: Drew's MCP server for Xcode integration
Project-URL: Homepage, https://github.com/drewster99/xcode-mcp-server
Project-URL: Repository, https://github.com/drewster99/xcode-mcp-server
Project-URL: Issues, https://github.com/drewster99/xcode-mcp-server/issues
Author-email: Andrew Benson <db@nuclearcyborg.com>
License: MIT
License-File: LICENSE
Keywords: mcp,server,xcode
Classifier: Development Status :: 3 - Alpha
Classifier: Intended Audience :: Developers
Classifier: License :: OSI Approved :: MIT License
Classifier: Programming Language :: Python :: 3
Classifier: Programming Language :: Python :: 3.8
Classifier: Programming Language :: Python :: 3.9
Classifier: Programming Language :: Python :: 3.10
Classifier: Programming Language :: Python :: 3.11
Classifier: Programming Language :: Python :: 3.12
Requires-Python: >=3.8
Requires-Dist: mcp[cli]>=1.2.0
Requires-Dist: questionary>=2.0.0
Requires-Dist: rich>=13.0.0
